{
    "name": "Lago Zancudo",
    "image": "images/lagozancudo.jpg",
    "enabled": true,
    "difficulty": "Medium",
    "time":
    {
        "hour": 7, 
        "minute": 0,
        "timestepEnabled": true
    },
    "weather": "FOGGY",
    "playerSpawnPoints":
    [
        {"pos": {"x": -2710.9052734375, "y": 2546.3850097656, "z": 2.7756412029266},"heading": 72.120079040527}
    ],
    "holes": 
    [
        {
            "pos": {"x": -2482.5925292969, "y": 2650.4748535156, "z": 3.2209451198578},
            "size": 3,
            "par": 3
        },
        {
            "pos": {"x": -2418.5319824219, "y": 2540.7905273438, "z": 2.4718062877655},
            "size": 3,
            "par": 3
        },
        {
            "pos": {"x": -2220.8835449219, "y": 2760.6906738281, "z": 3.3622760772705},
            "size": 3,
            "par": 3
        },
        {
            "pos": {"x": -2096.4770507812, "y": 2499.6989746094, "z": 3.6081738471985},
            "size": 3,
            "par": 3
        },
        {
            "pos": {"x": -1769.2279052734, "y": 2637.3364257812, "z": 2.1377267837524},
            "size": 2,
            "par": 4
        },
        {
            "pos": {"x": -1539.11328125, "y": 2490.8850097656, "z": 3.5884602069855},
            "size": 3,
            "par": 3
        },
        {
            "pos": {"x": -1440.3924560547, "y": 2658.7734375, "z": 17.671781539917},
            "size": 3,
            "par": 5
        }
    ],
    "invisibleObjects":
    {
    },
    "objectSpawnPoints":
    [
    ]
}